{
  "slug": "daikoku-umizuri-shisetsu",
  "name": "大黒海づり施設",
  "location": {
    "latitude": 35.4487057,
    "longitude": 139.6945202
  },
  "area": {
    "prefecture": "神奈川県",
    "pref_slug": "kanagawa",
    "area_name": "東京湾",
    "area_slug": "tokyobay",
    "city": "横浜市",
    "city_slug": "yokohama"
  },
  "physical_features": {
    "sea_bearing_deg": 125,
    "seabed_type": "shell",
    "surfer_spot": false,
    "nearest_20m_contour_distance_m": 811.0
  },
  "derived_features": {
    "bottom_kisugo_score": 65,
    "seabed_summary": "貝殻主体、貝殻混じり"
  },
  "info": {
    "notes": "有料桟橋式施設、アジ・イワシ・タコ・スズキ向き、道具貸出あり",
    "access": "横浜市方面から車利用",
    "lead_text": "横浜港の入口、大黒ふ頭に設けられた有料の桟橋式海釣り施設です。赤灯台が目印の釣りデッキは全長200m超で、足元の水深は約7.5mあります。潮通しのよさから大型のスズキも回遊してきます。桟橋先端の東京湾側はスズキ・フッコのルアー狙いで特に人気が高く、開園前から整理券待ちの列ができることも。入場者数が180名を超えるとルアー使用に制限がかかるため、平日の朝イチが狙い目です。"
  },
  "classification": {
    "primary_type": "fishing_facility",
    "confidence": 0.95,
    "secondary_flags": [
      "pier"
    ],
    "source": "osm_rule",
    "osm_evidence": [
      "leisure=fishing@7m",
      "man_made=pier@19m"
    ]
  },
  "target_fish": [
    "suzuki",
    "iwashi",
    "tako",
    "aji"
  ],
  "harbor_code": "14-4",
  "harbor_name": "新山下"
}
