{
  "slug": "kambara-kaigan",
  "name": "蒲原海岸",
  "location": {
    "latitude": 35.1157181,
    "longitude": 138.6045721
  },
  "area": {
    "prefecture": "静岡県",
    "pref_slug": "shizuoka",
    "area_name": "駿河湾",
    "area_slug": "suruga-bay",
    "city": "静岡市",
    "city_slug": "shizuoka"
  },
  "physical_features": {
    "sea_bearing_deg": 185,
    "seabed_type": "sand",
    "surfer_spot": false,
    "nearest_20m_contour_distance_m": 188.2
  },
  "derived_features": {
    "bottom_kisugo_score": 85,
    "seabed_summary": "砂主体",
    "terrain_summary": ""
  },
  "info": {
    "notes": "穏やかな砂浜、投げ釣りでキス・イシモチ",
    "access": "蒲原駅から徒歩10分",
    "photo_url": ""
  },
  "classification": {
    "primary_type": "sand_beach",
    "confidence": 1.0,
    "secondary_flags": [],
    "source": "manual",
    "osm_evidence": []
  },
  "target_fish": [
    "shirogisu"
  ]
}
