{
  "slug": "katsuyama-kaigan",
  "name": "勝山海岸",
  "location": {
    "latitude": 35.1167961,
    "longitude": 139.8284362
  },
  "area": {
    "prefecture": "千葉県",
    "pref_slug": "chiba",
    "area_name": "内房",
    "area_slug": "uchibo",
    "city": "鋸南町",
    "city_slug": "kyonan"
  },
  "physical_features": {
    "sea_bearing_deg": 285.3,
    "seabed_type": "sand",
    "surfer_spot": false,
    "nearest_20m_contour_distance_m": 399.4
  },
  "derived_features": {
    "bottom_kisugo_score": 80,
    "seabed_summary": "砂主体、近傍に石要素あり"
  },
  "info": {
    "notes": "勝山港に隣接する砂浜、キス・マゴチ向きサーフ",
    "access": "安房勝山駅から徒歩10分",
    "lead_text": "砂地から根際を攻められる変化に富んだ地形です。シロギスは初夏から秋口にかけての日中、マゴチは夏場の朝まずめに実績が高く、常連は佐久間川河口寄りの流れが当たるポイントを好んで狙います。"
  },
  "classification": {
    "primary_type": "sand_beach",
    "confidence": 0.59,
    "secondary_flags": [],
    "source": "osm_rule",
    "osm_evidence": [
      "natural=beach@141m"
    ]
  },
  "target_fish": [
    "magochi",
    "shirogisu"
  ],
  "harbor_code": "12-10",
  "harbor_name": "岩井袋",
  "updated_at": "2026-04-18",
  "jma_harbor_code": "TT"
}
