{
  "slug": "marine-park-omaezaki",
  "name": "マリンパーク御前崎",
  "location": {
    "latitude": 34.6067212,
    "longitude": 138.2268788
  },
  "area": {
    "prefecture": "静岡県",
    "pref_slug": "shizuoka",
    "area_name": "駿河湾",
    "area_slug": "suruga-bay",
    "city": "御前崎市",
    "city_slug": "omaezaki"
  },
  "physical_features": {
    "sea_bearing_deg": 50,
    "seabed_type": "rock",
    "surfer_spot": false,
    "nearest_20m_contour_distance_m": null
  },
  "derived_features": {
    "bottom_kisugo_score": 35,
    "seabed_summary": "石・岩主体、貝殻混じり、近傍に石要素あり",
    "terrain_summary": ""
  },
  "info": {
    "notes": "整備された護岸・公園、初心者・ファミリー向き",
    "access": "御前崎市方面から車利用",
    "photo_url": "",
    "lead_text": "この釣り場は現在釣り禁止となりました。"
  },
  "classification": {
    "primary_type": "sand_beach",
    "confidence": 1.0,
    "secondary_flags": [
      "parking_nearby"
    ],
    "source": "manual",
    "osm_evidence": [
      "natural=beach@213m",
      "natural=beach@245m"
    ]
  },
  "target_fish": [],
  "harbor_code": "22-17",
  "harbor_name": "御前崎",
  "updated_at": "2026-04-18"
}
