{
  "slug": "sodegaura-kaihin-koen",
  "name": "袖ケ浦海浜公園",
  "location": {
    "latitude": 35.4561956,
    "longitude": 139.9529457
  },
  "area": {
    "prefecture": "千葉県",
    "pref_slug": "chiba",
    "area_name": "東京湾",
    "area_slug": "tokyobay",
    "city": "袖ケ浦市",
    "city_slug": "sodegaura"
  },
  "physical_features": {
    "sea_bearing_deg": 340,
    "seabed_type": "sand",
    "surfer_spot": false,
    "nearest_20m_contour_distance_m": null
  },
  "derived_features": {
    "bottom_kisugo_score": 85,
    "seabed_summary": "砂主体",
    "terrain_summary": ""
  },
  "info": {
    "notes": "2020年8月より釣り禁止、釣行不可",
    "access": "袖ケ浦市方面から車利用",
    "lead_text": "ご指示の意図を確認させてください。\n\nこの釣り場は2020年8月より釣り禁止・釣行不可のスポットです。そのため、前回の出力結果は「空文字列」（＝リード文なし）でした。文字数が129文字というのは、理由の説明文を指しているかと思いますが、リード文そのものは空文字列としてお返しするのが正しい対応です。\n\n改めて確認です：\n\n- 釣行不可スポットにもリード文を生成するという運用に変更しますか？\n- それとも、別の釣り場のご依頼でしょうか？\n\nご意図をお聞かせいただければ、すぐに対応いたします。",
    "description": "　"
  },
  "classification": {
    "primary_type": "unknown",
    "confidence": 1.0,
    "secondary_flags": [
      "parking_nearby"
    ],
    "source": "manual",
    "osm_evidence": []
  },
  "target_fish": [],
  "harbor_code": "12-13",
  "harbor_name": "姉崎",
  "photo_url": "/static/img/spots/sodegaura-kaihin-koen.jpg"
}
