{
  "slug": "tarui-fishing-port",
  "name": "樽井漁港",
  "location": {
    "latitude": 34.3811163,
    "longitude": 135.2583772
  },
  "area": {
    "prefecture": "大阪府",
    "pref_slug": "osaka",
    "area_name": "大阪湾",
    "area_slug": "osakawan",
    "city": "泉南市",
    "city_slug": "sennan"
  },
  "physical_features": {
    "sea_bearing_deg": 311.8,
    "seabed_type": "unknown",
    "surfer_spot": false,
    "nearest_20m_contour_distance_m": null
  },
  "derived_features": {
    "bottom_kisugo_score": 50,
    "seabed_summary": ""
  },
  "info": {
    "notes": "阪南市の漁港。アジ・クロダイ・メバル・カサゴが釣れる小規模な漁港。",
    "access": "樽井駅から徒歩20分"
  },
  "classification": {
    "primary_type": "fishing_facility",
    "confidence": 0.55,
    "secondary_flags": [
      "pier"
    ],
    "source": "osm_rule",
    "osm_evidence": [
      "man_made=pier@133m",
      "natural=beach@211m"
    ]
  },
  "target_fish": [
    "kurodai",
    "kasago",
    "mebaru",
    "aji"
  ],
  "harbor_code": "27-2",
  "harbor_name": "淡輪"
}
