{
  "slug": "toshijima",
  "name": "答志島",
  "location": {
    "latitude": 34.5205947,
    "longitude": 136.8810135
  },
  "area": {
    "prefecture": "三重県",
    "pref_slug": "mie",
    "area_name": "志摩・南伊勢",
    "area_slug": "shima-minami-ise",
    "city": "鳥羽市",
    "city_slug": "toba"
  },
  "physical_features": {
    "sea_bearing_deg": 0,
    "seabed_type": "sand",
    "surfer_spot": false,
    "nearest_20m_contour_distance_m": 1411.9
  },
  "derived_features": {
    "bottom_kisugo_score": 80,
    "seabed_summary": "砂主体、近傍に石要素あり",
    "terrain_summary": ""
  },
  "info": {
    "notes": "鳥羽市の離島漁港、アジ・グレ・アオリイカ向き",
    "access": "鳥羽市方面から車利用",
    "photo_url": "",
    "lead_text": "鳥羽市沖に浮かぶ離島・答志島には、答志港・和具港・桃取港と複数の漁港があり、それぞれ異なる釣り場の顔を持ちます。メジナは答志新港・海水浴場側の堤防で秋から春にかけての実績が高く、アオリイカは旧港の八幡神社側堤防が知られたポイントです。アジは11月〜12月の夕マズメ以降が数釣りの本番ですが、答志漁港ではアミエビの使用が禁止されているため注意が必要です。ワカメ加工の時期には茹で汁が港内に入り水温が不安定になるという、離島ならではの事情もあります。"
  },
  "classification": {
    "primary_type": "fishing_facility",
    "confidence": 1.0,
    "secondary_flags": [],
    "source": "manual",
    "osm_evidence": []
  },
  "target_fish": [
    "aji",
    "mejina",
    "aoriika"
  ],
  "harbor_code": "24-5",
  "harbor_name": "鳥羽",
  "updated_at": "2026-04-18",
  "jma_harbor_code": "TB"
}
