{
  "slug": "nojima-koen",
  "name": "野島公園",
  "location": {
    "latitude": 35.328291,
    "longitude": 139.636488
  },
  "area": {
    "prefecture": "神奈川県",
    "pref_slug": "kanagawa",
    "area_name": "東京湾",
    "area_slug": "tokyobay",
    "city": "横須賀市",
    "city_slug": "yokosuka"
  },
  "physical_features": {
    "sea_bearing_deg": 25,
    "seabed_type": "unknown",
    "depth_near_m": null,
    "depth_far_m": null,
    "surfer_spot": false,
    "nearest_20m_contour_distance_m": null
  },
  "derived_features": {
    "bottom_kisugo_score": 50,
    "terrain_summary": "傾斜不明"
  },
  "info": {
    "notes": "岸壁と浜がある公園",
    "access": "野島公園駅から徒歩5分",
    "photo_url": "https://raw.githubusercontent.com/sgrhirose-tech/fishing/resources/photos/nojima-koen.jpg"
  }
}